ppt_mcp_server.py
ppt_utils.py
mseep_office_powerpoint_mcp_server-1.0.2.dist-info/METADATA
mseep_office_powerpoint_mcp_server-1.0.2.dist-info/WHEEL
mseep_office_powerpoint_mcp_server-1.0.2.dist-info/entry_points.txt
mseep_office_powerpoint_mcp_server-1.0.2.dist-info/licenses/LICENSE
mseep_office_powerpoint_mcp_server-1.0.2.dist-info/RECORD
