Metadata-Version: 2.4
Name: mseep-office-powerpoint-mcp-server
Version: 1.0.2
Summary: MCP Server for PowerPoint manipulation using python-pptx
Author-email: mseep <support@skydeck.ai>
Maintainer-email: mseep <support@skydeck.ai>
License: MIT License
License-File: LICENSE
Classifier: License :: OSI Approved :: MIT License
Classifier: Operating System :: OS Independent
Classifier: Programming Language :: Python :: 3
Requires-Python: >=3.6
Requires-Dist: mcp[cli]>=1.3.0
Requires-Dist: python-pptx>=0.6.21
